pymt_geotiff/__init__.py
pymt_geotiff/bmi.py
pymt_geotiff/data/GeoTiff/api.yaml
pymt_geotiff/data/GeoTiff/bmi-geotiff.yaml
pymt_geotiff/data/GeoTiff/info.yaml
pymt_geotiff/data/GeoTiff/parameters.yaml
pymt_geotiff/data/GeoTiff/run.yaml
pymt_geotiff-0.2.1.dist-info/LICENSE
pymt_geotiff-0.2.1.dist-info/METADATA
pymt_geotiff-0.2.1.dist-info/WHEEL
pymt_geotiff-0.2.1.dist-info/entry_points.txt
pymt_geotiff-0.2.1.dist-info/top_level.txt
pymt_geotiff-0.2.1.dist-info/RECORD
