Metadata-Version: 2.1
Name: pymt_geotiff
Version: 0.2.1
Summary: PyMT plugin for pymt_geotiff
Home-page: https://github.com/mdpiper/pymt_geotiff
Author: Mark Piper
Author-email: mark.piper@colorado.edu
Keywords: bmi,pymt
Classifier: Development Status :: 4 - Beta
Classifier: Intended Audience :: Science/Research
Classifier: License :: OSI Approved :: MIT License
Classifier: Operating System :: OS Independent
Classifier: Programming Language :: Python :: 3.10
Classifier: Programming Language :: Python :: 3.11
Classifier: Programming Language :: Python :: 3.12
Classifier: Programming Language :: Python :: 3.13
Classifier: Programming Language :: Python :: 3
Classifier: Programming Language :: Python :: Implementation :: CPython
Classifier: Topic :: Scientific/Engineering :: Physics
License-File: LICENSE
Requires-Dist: numpy
